Metadata-Version: 2.1
Name: bridget
Version: 0.2.3
Summary: BridgET Evapotranspiration toolbox for Python
Home-page: UNKNOWN
Author: Mirko Mälicke
Author-email: mirko.maelicke@kit.edu
License: MIT License
Platform: UNKNOWN
